googlemaps/__init__.py
googlemaps/client.py
googlemaps/convert.py
googlemaps/directions.py
googlemaps/distance_matrix.py
googlemaps/elevation.py
googlemaps/exceptions.py
googlemaps/geocoding.py
googlemaps/geolocation.py
googlemaps/places.py
googlemaps/roads.py
googlemaps/timezone.py
googlemapsaleks57-3.0.2.dist-info/AUTHORS
googlemapsaleks57-3.0.2.dist-info/LICENSE
googlemapsaleks57-3.0.2.dist-info/METADATA
googlemapsaleks57-3.0.2.dist-info/WHEEL
googlemapsaleks57-3.0.2.dist-info/top_level.txt
googlemapsaleks57-3.0.2.dist-info/RECORD
